poetry_demo_cs151/__init__.py
poetry_demo_cs151/main.py
poetry_demo_cs151-0.4.0.dist-info/WHEEL
poetry_demo_cs151-0.4.0.dist-info/METADATA
poetry_demo_cs151-0.4.0.dist-info/RECORD
