Metadata-Version: 2.1
Name: poetry-demo-cs151
Version: 0.4.0
Summary: basic poetry project to explore poetry tool
Author: Craig Saxton
Author-email: csaxton171@gmail.com
Requires-Python: >=3.7,<4.0
Classifier: Programming Language :: Python :: 3
Classifier: Programming Language :: Python :: 3.7
Classifier: Programming Language :: Python :: 3.8
